build_influence/__init__.py
build_influence/cli.py
build_influence/constants.py
build_influence/analysis/__init__.py
build_influence/analysis/analyzer.py
build_influence/analysis/feature_identifier.py
build_influence/commands/__init__.py
build_influence/commands/analyze.py
build_influence/commands/generate.py
build_influence/commands/interactive_workflow.py
build_influence/commands/interview.py
build_influence/commands/logs.py
build_influence/commands/publish.py
build_influence/config/__init__.py
build_influence/config/loader.py
build_influence/generation/__init__.py
build_influence/generation/base_generator.py
build_influence/generation/devto_generator.py
build_influence/generation/generator.py
build_influence/generation/linkedin_generator.py
build_influence/generation/twitter_generator.py
build_influence/interview/__init__.py
build_influence/interview/interviewer.py
build_influence/publication/__init__.py
build_influence/publication/base_publisher.py
build_influence/publication/devto_publisher.py
build_influence/publication/linkedin_publisher.py
build_influence/publication/twitter_publisher.py
build_influence/utils/__init__.py
build_influence/utils/logging.py
build_influence-0.1.3.dist-info/METADATA
build_influence-0.1.3.dist-info/WHEEL
build_influence-0.1.3.dist-info/entry_points.txt
build_influence-0.1.3.dist-info/top_level.txt
build_influence-0.1.3.dist-info/RECORD
