Metadata-Version: 2.4
Name: build_influence
Version: 0.1.3
Requires-Dist: litellm
Requires-Dist: mcp
Requires-Dist: loguru
Requires-Dist: pytest
Requires-Dist: typer[all]
Requires-Dist: pyyaml
Requires-Dist: python-dotenv
Requires-Dist: python-box
Requires-Dist: tqdm
Requires-Dist: rich
Dynamic: requires-dist
